{
  "source": "jun sqlite snapshot",
  "updatedAt": "2026-04-01T04:25:00.296Z",
  "window": "~4 min",
  "checkpointRange": {
    "latestCheckpoint": 260285444
  },
  "networkStats": {
    "epoch": 1084,
    "validatorCount": 127,
    "avgFinalityMs": 259,
    "totalTx": 8371,
    "uniqueWallets": 753,
    "newWallets": 753,
    "windowDurationSeconds": 268,
    "windowCheckpoints": 1000
  },
  "checkpoints": [
    {
      "checkpoint": 260285444,
      "txCount": 3,
      "eventCount": 0,
      "finalitySeconds": 0.272,
      "timestamp": "2026-04-01T04:24:44.629Z"
    },
    {
      "checkpoint": 260285443,
      "txCount": 9,
      "eventCount": 22,
      "finalitySeconds": 0.24,
      "timestamp": "2026-04-01T04:24:44.357Z"
    },
    {
      "checkpoint": 260285442,
      "txCount": 6,
      "eventCount": 8,
      "finalitySeconds": 0.253,
      "timestamp": "2026-04-01T04:24:44.117Z"
    },
    {
      "checkpoint": 260285441,
      "txCount": 14,
      "eventCount": 31,
      "finalitySeconds": 0.23,
      "timestamp": "2026-04-01T04:24:43.864Z"
    },
    {
      "checkpoint": 260285440,
      "txCount": 3,
      "eventCount": 21,
      "finalitySeconds": 0.244,
      "timestamp": "2026-04-01T04:24:43.634Z"
    },
    {
      "checkpoint": 260285439,
      "txCount": 3,
      "eventCount": 12,
      "finalitySeconds": 0.219,
      "timestamp": "2026-04-01T04:24:43.390Z"
    },
    {
      "checkpoint": 260285438,
      "txCount": 4,
      "eventCount": 8,
      "finalitySeconds": 0.293,
      "timestamp": "2026-04-01T04:24:43.171Z"
    },
    {
      "checkpoint": 260285437,
      "txCount": 6,
      "eventCount": 26,
      "finalitySeconds": 0.231,
      "timestamp": "2026-04-01T04:24:42.878Z"
    },
    {
      "checkpoint": 260285436,
      "txCount": 5,
      "eventCount": 4,
      "finalitySeconds": 0.263,
      "timestamp": "2026-04-01T04:24:42.647Z"
    },
    {
      "checkpoint": 260285435,
      "txCount": 10,
      "eventCount": 40,
      "finalitySeconds": 0.247,
      "timestamp": "2026-04-01T04:24:42.384Z"
    },
    {
      "checkpoint": 260285434,
      "txCount": 5,
      "eventCount": 46,
      "finalitySeconds": 0.317,
      "timestamp": "2026-04-01T04:24:42.137Z"
    },
    {
      "checkpoint": 260285433,
      "txCount": 9,
      "eventCount": 34,
      "finalitySeconds": 0.284,
      "timestamp": "2026-04-01T04:24:41.820Z"
    },
    {
      "checkpoint": 260285432,
      "txCount": 9,
      "eventCount": 14,
      "finalitySeconds": 0.259,
      "timestamp": "2026-04-01T04:24:41.536Z"
    },
    {
      "checkpoint": 260285431,
      "txCount": 6,
      "eventCount": 8,
      "finalitySeconds": 0.302,
      "timestamp": "2026-04-01T04:24:41.277Z"
    },
    {
      "checkpoint": 260285430,
      "txCount": 15,
      "eventCount": 57,
      "finalitySeconds": 0.258,
      "timestamp": "2026-04-01T04:24:40.975Z"
    },
    {
      "checkpoint": 260285429,
      "txCount": 4,
      "eventCount": 15,
      "finalitySeconds": 0.28,
      "timestamp": "2026-04-01T04:24:40.717Z"
    },
    {
      "checkpoint": 260285428,
      "txCount": 7,
      "eventCount": 14,
      "finalitySeconds": 0.248,
      "timestamp": "2026-04-01T04:24:40.437Z"
    },
    {
      "checkpoint": 260285427,
      "txCount": 4,
      "eventCount": 5,
      "finalitySeconds": 0.263,
      "timestamp": "2026-04-01T04:24:40.189Z"
    },
    {
      "checkpoint": 260285426,
      "txCount": 8,
      "eventCount": 8,
      "finalitySeconds": 0.225,
      "timestamp": "2026-04-01T04:24:39.926Z"
    },
    {
      "checkpoint": 260285425,
      "txCount": 4,
      "eventCount": 5,
      "finalitySeconds": null,
      "timestamp": "2026-04-01T04:24:39.701Z"
    }
  ],
  "topContracts": [
    {
      "label": "0x9e208bed81b7072fa75af8f9eaca42ced3ec8154bb04f5b948c2a9455125d136::interface",
      "activity": 6530,
      "wallets": 7
    },
    {
      "label": "0x73949528d57ccc07dad6d0eb996bae9ac66cb5c2189f08072104b060190add3d::interface",
      "activity": 5832,
      "wallets": 1
    },
    {
      "label": "0xe8e485e9339ec1d42ac92350fd3708ba823ad6e813af459fa32c68562e413cda::dbke",
      "activity": 5456,
      "wallets": 6
    },
    {
      "label": "0xcaf6ba059d539a97646d47f0b9ddf843e138d215e2a12ca1f4585d386f7aec3a::pool",
      "activity": 4387,
      "wallets": 5
    },
    {
      "label": "0x5ea2c97771334e4a64216d42e5ba68eb2a9792fe874c8d2bfdf8feb32ec7dc8b::lotus_db_vault",
      "activity": 1430,
      "wallets": 1
    },
    {
      "label": "0xa6d0bd2e53216880182395e83f66ca581bb3ece53f154f54b2cc6b2403f66af7::entrypoint",
      "activity": 1070,
      "wallets": 1
    },
    {
      "label": "0x2c8d603bc51326b8c13cef9dd07031a408a48dddb541963357661df5d3204809::pool",
      "activity": 957,
      "wallets": 4
    },
    {
      "label": "0x4979543452f609ff272d504755966ff5e70122256101c17adbe8bd27d35116c3::price_data_pull_v2",
      "activity": 891,
      "wallets": 1
    },
    {
      "label": "0xe25c44519b9b2eff67ada9b823db0eca3e801a801ce9050d2082268b7d902397::deepbookv3",
      "activity": 569,
      "wallets": 10
    },
    {
      "label": "0xb08bcde904ec0a9c632b2e7e000207d69c802b3c896506489decc443c599e436::m",
      "activity": 472,
      "wallets": 1
    }
  ],
  "activeWallets": [
    {
      "label": "0xffd4f043057226453aeba59732d41c6093516f54823ebc3a16d17f8a77d2f0ad",
      "actions": 1309,
      "lastSeen": "2026-04-01T04:24:44.357Z"
    },
    {
      "label": "0xcde6dbe01902be1f200ff03dbbd149e586847be8cee15235f82750d9b06c0e04",
      "actions": 1196,
      "lastSeen": "2026-04-01T04:24:44.357Z"
    },
    {
      "label": "0x0feb54a725aa357ff2f5bc6bb023c05b310285bd861275a30521f339a434ebb3",
      "actions": 630,
      "lastSeen": "2026-04-01T04:24:43.864Z"
    },
    {
      "label": "0xc0c901d76288c47eb45c0b3c4fb92b2b3992316553e36a62a5aa2da04935d11a",
      "actions": 439,
      "lastSeen": "2026-04-01T04:24:44.629Z"
    },
    {
      "label": "0x99b467ddd9476cbab3ef4276b8d094d522387a9789a54655cda938b8439a8c09",
      "actions": 366,
      "lastSeen": "2026-04-01T04:24:44.357Z"
    },
    {
      "label": "0xa03e7b8b5caf7799becceaac41deba8e9ac0b07902235f55aaea9e60d1abb316",
      "actions": 314,
      "lastSeen": "2026-04-01T04:24:43.864Z"
    },
    {
      "label": "0x77776760c06997206b13fa76f127aa016d24a645f04fce516be153ece0bddf23",
      "actions": 299,
      "lastSeen": "2026-04-01T04:24:38.001Z"
    },
    {
      "label": "0xe289ecacdf462017d459a419393863dc89f3d61daf3af5ecc1d380172e7e61a7",
      "actions": 217,
      "lastSeen": "2026-04-01T04:24:41.820Z"
    },
    {
      "label": "0xa0766ff7b0325c18e4c7416ad4ea4d01e92f09147b8c5e7e4a582dc84ca3a874",
      "actions": 143,
      "lastSeen": "2026-04-01T04:24:41.820Z"
    },
    {
      "label": "0xd265672730b0540ffd3569530682a0f02ef984b703457790554eb0e19329663a",
      "actions": 141,
      "lastSeen": "2026-04-01T04:24:35.378Z"
    }
  ]
}